time_series/__init__.py
time_series/components/__init__.py
time_series/components/decoder/__init__.py
time_series/components/decoder/mlp.py
time_series/components/distributions/__init__.py
time_series/components/distributions/generalized_pareto.py
time_series/components/distributions/univariate_binned.py
time_series/components/distributions/univariate_splice_binned_pareto.py
time_series/components/encoder/__init__.py
time_series/components/encoder/tcn.py
4996-0.1.1.dist-info/LICENSE
4996-0.1.1.dist-info/METADATA
4996-0.1.1.dist-info/WHEEL
4996-0.1.1.dist-info/top_level.txt
4996-0.1.1.dist-info/RECORD
