Metadata-Version: 2.1
Name: 4996
Version: 0.1.1
Summary: Nothing to see here.
Home-page: https://github.com/theoldfather/time-series
Author: Jeremy Oldfather
Author-email: contact@jeremyoldfather.com
License: Apache
Platform: UNKNOWN
Classifier: License :: OSI Approved :: Apache Software License
Classifier: Programming Language :: Python :: 3
Classifier: Programming Language :: Python :: 3.7
License-File: LICENSE
Requires-Dist: torch (==1.10.1)
Requires-Dist: pandas
Requires-Dist: numpy
